qutrunk/__init__.py
qutrunk/algorithm/__init__.py
qutrunk/algorithm/vqe.py
qutrunk/backends/__init__.py
qutrunk/backends/backend.py
qutrunk/backends/braket/__init__.py
qutrunk/backends/braket/adapter.py
qutrunk/backends/braket/braket.py
qutrunk/backends/braket/braket_job.py
qutrunk/backends/braket/exception.py
qutrunk/backends/ibm/__init__.py
qutrunk/backends/ibm/ibm.py
qutrunk/backends/ibm/ibm_client.py
qutrunk/backends/local/__init__.py
qutrunk/backends/local/exceptions.py
qutrunk/backends/local/local.py
qutrunk/backends/local/local_impl.py
qutrunk/backends/local/sim_distribute.py
qutrunk/backends/local/sim_gpu.py
qutrunk/backends/local/sim_local.py
qutrunk/backends/qusaas/__init__.py
qutrunk/backends/qusaas/httpclient.py
qutrunk/backends/qusaas/qusaas.py
qutrunk/backends/qusprout/__init__.py
qutrunk/backends/qusprout/qusprout.py
qutrunk/backends/qusprout/rpcclient.py
qutrunk/backends/result.py
qutrunk/circuit/__init__.py
qutrunk/circuit/bit.py
qutrunk/circuit/circuit.py
qutrunk/circuit/classical_bit.py
qutrunk/circuit/classical_reg.py
qutrunk/circuit/command.py
qutrunk/circuit/counter.py
qutrunk/circuit/gates/__init__.py
qutrunk/circuit/gates/_utils.py
qutrunk/circuit/gates/barrier.py
qutrunk/circuit/gates/basicgate.py
qutrunk/circuit/gates/cr.py
qutrunk/circuit/gates/h.py
qutrunk/circuit/gates/i.py
qutrunk/circuit/gates/iswap.py
qutrunk/circuit/gates/measure.py
qutrunk/circuit/gates/meta.py
qutrunk/circuit/gates/p.py
qutrunk/circuit/gates/r.py
qutrunk/circuit/gates/reset.py
qutrunk/circuit/gates/rx.py
qutrunk/circuit/gates/rxx.py
qutrunk/circuit/gates/ry.py
qutrunk/circuit/gates/ryy.py
qutrunk/circuit/gates/rz.py
qutrunk/circuit/gates/rzz.py
qutrunk/circuit/gates/s.py
qutrunk/circuit/gates/sdg.py
qutrunk/circuit/gates/sqrtswap.py
qutrunk/circuit/gates/sqrtx.py
qutrunk/circuit/gates/swap.py
qutrunk/circuit/gates/sxdg.py
qutrunk/circuit/gates/t.py
qutrunk/circuit/gates/tdg.py
qutrunk/circuit/gates/u1.py
qutrunk/circuit/gates/u2.py
qutrunk/circuit/gates/u3.py
qutrunk-0.2.2.dist-info/LICENSE
qutrunk-0.2.2.dist-info/WHEEL
qutrunk-0.2.2.dist-info/METADATA
qutrunk-0.2.2.dist-info/RECORD
