Metadata-Version: 2.1
Name: qutrunk
Version: 0.2.2
Summary: qutrunk is an open source library for quantum computing.
Home-page: http://www.qudoor.com/
License: Apache-2.0
Keywords: qutrunk,quantum,sdk
Author: qudoorzh2022
Author-email: qudoorzh2022@163.com
Requires-Python: >=3.8,<3.11
Classifier: License :: OSI Approved :: Apache Software License
Classifier: Operating System :: MacOS
Classifier: Operating System :: Microsoft :: Windows
Classifier: Operating System :: POSIX :: Linux
Classifier: Programming Language :: Python :: 3
Classifier: Programming Language :: Python :: 3.10
Classifier: Programming Language :: Python :: 3.8
Classifier: Programming Language :: Python :: 3.9
Classifier: Topic :: Software Development :: Libraries :: Python Modules
Provides-Extra: braket
Provides-Extra: gpu
Provides-Extra: parallel
Requires-Dist: amazon-braket-sdk (>=1.32.0,<2.0.0); extra == "braket"
Requires-Dist: mpi4py (>=3.1.4,<4.0.0); extra == "parallel"
Requires-Dist: networkx (>=2.8,<3.0)
Requires-Dist: numba (>=0.56.4,<0.57.0); extra == "gpu"
Requires-Dist: numpy (>=1.21.6,<2.0.0)
Requires-Dist: ply (>=3.11,<4.0)
Requires-Dist: pyyaml (>=6.0,<7.0)
Requires-Dist: requests (>=2.27.1,<3.0.0)
Requires-Dist: retworkx (>=0.11.0,<0.12.0)
Requires-Dist: thrift (>=0.15.0,<0.16.0)
Project-URL: Documentation, http://developer.queco.cn/qutrunk_api/
Project-URL: Repository, https://github.com/queco-quantum/qutrunk
